django_stripe/__init__.py
django_stripe/admin.py
django_stripe/apps.py
django_stripe/conf.py
django_stripe/exceptions.py
django_stripe/logging.py
django_stripe/models.py
django_stripe/payments.py
django_stripe/serializers.py
django_stripe/signal_receivers.py
django_stripe/signals.py
django_stripe/tests.py
django_stripe/types.py
django_stripe/urls.py
django_stripe/utils.py
django_stripe/view_mixins.py
django_stripe/views.py
django_stripe_subs-0.3.dist-info/LICENSE.txt
django_stripe_subs-0.3.dist-info/METADATA
django_stripe_subs-0.3.dist-info/WHEEL
django_stripe_subs-0.3.dist-info/top_level.txt
django_stripe_subs-0.3.dist-info/RECORD
