Metadata-Version: 2.1
Name: django-stripe-subs
Version: 0.3
Summary: Easier management of subscriptions with Stripe in Django
Home-page: https://github.com/primal100/django_stripe
Author: Paul Martin
License: UNKNOWN
Platform: UNKNOWN
Classifier: Development Status :: 4 - Beta
Classifier: Programming Language :: Python :: 3.6
Classifier: Programming Language :: Python :: 3.7
Classifier: Programming Language :: Python :: 3.8
Classifier: Programming Language :: Python :: 3.9
Classifier: License :: OSI Approved :: MIT License
Classifier: Operating System :: OS Independent
License-File: LICENSE.txt
Requires-Dist: django
Requires-Dist: djangorestframework
Requires-Dist: inflect
Requires-Dist: stripe
Requires-Dist: stripe-subscriptions
Requires-Dist: typing-extensions (>=3.10.0.0) ; python_version < "3.8"
